<?xml version="1.0" encoding="UTF-8"?>
<objects serializationModel="Studio.02.02.00">
	<object class="AudioFile" id="{00a9c5a1-6cc7-4430-9e11-25400e5b4052}">
		<property name="assetPath">
			<value>Halo 2/sadstrings_nl~loop.ogg</value>
		</property>
		<property name="isStreaming">
			<value>true</value>
		</property>
		<property name="frequencyInKHz">
			<value>44.0999985</value>
		</property>
		<property name="channelCount">
			<value>2</value>
		</property>
		<property name="length">
			<value>92.882721088435375</value>
		</property>
		<relationship name="masterAssetFolder">
			<destination>{50b460cc-7451-46f8-8f34-2d9189a2e78e}</destination>
		</relationship>
	</object>
</objects>
